{
  "audio": {
    "sample_rate": 44100,
    "n_fft": 2048,
    "hop_length": 256,
    "chunk_seconds": 3.0
  },
  "model": {
    "d_model": 256,
    "n_heads": 4,
    "n_encoder_layers": 4,
    "n_decoder_layers": 4,
    "n_bottleneck_layers": 6,
    "dropout": 0.0,
    "d_state": 32,
    "use_mid_side": false,
    "ssm_variant": "mamba3",
    "d_conv": 4,
    "expand": 2,
    "mamba3_headdim": 64,
    "mamba3_is_mimo": false,
    "mamba3_mimo_rank": 4,
    "mamba3_chunk_size": 32,
    "mamba3_is_outproj_norm": false
  },
  "loss": {
    "mag_weight": 0.25,
    "mr_stft_weight": 0.0,
    "si_sdr_weight": 0.5,
    "spectral_sdr_weight": 0.0,
    "band_weight": 1.25
  },
  "training": {
    "batch_size": 1,
    "learning_rate": 1e-4,
    "weight_decay": 0.005,
    "warmup_steps": 1000,
    "max_steps": 10000,
    "gradient_accumulation": 8,
    "max_grad_norm": 1.0,
    "save_every_steps": 200,
    "eval_every_steps": 500,
    "log_every_steps": 25,
    "use_amp": true,
    "gradient_checkpointing": "encoder",
    "num_workers": 0,
    "prefetch_factor": 2
  },
  "experiment_name": "vocal_separator_mamba3",
  "seed": 42
}
